crypto_utils/security.py
aiops_crypto_utils-0.0.2.dist-info/METADATA
aiops_crypto_utils-0.0.2.dist-info/WHEEL
aiops_crypto_utils-0.0.2.dist-info/top_level.txt
aiops_crypto_utils-0.0.2.dist-info/RECORD
